emtable/__init__.py
emtable/metadata.py
emtable-0.0.14.dist-info/LICENSE
emtable-0.0.14.dist-info/METADATA
emtable-0.0.14.dist-info/WHEEL
emtable-0.0.14.dist-info/top_level.txt
emtable-0.0.14.dist-info/RECORD
