Metadata-Version: 2.1
Name: emtable
Version: 0.0.14
Summary: Simple module to deal with EM tabular data (aka metadata)
Home-page: https://github.com/delarosatrevin/emtable
Author: J.M. De la Rosa Trevin, Grigory Sharov
Author-email: delarosatrevin@gmail.com, gsharov@mrc-lmb.cam.ac.uk
License: UNKNOWN
Project-URL: Bug Reports, https://github.com/delarosatrevin/emtable/issues
Project-URL: Source, https://github.com/delarosatrevin/emtable
Keywords: electron-microscopy cryo-em structural-biology image-processing
Platform: UNKNOWN
Classifier: Development Status :: 5 - Production/Stable
Classifier: License :: OSI Approved :: GNU General Public License v3 (GPLv3)
Classifier: Programming Language :: Python :: 3
